utils/helpers.py
utils/spotify.py
saberio_rewind-1.0.3.post3.dist-info/LICENSE
saberio_rewind-1.0.3.post3.dist-info/METADATA
saberio_rewind-1.0.3.post3.dist-info/WHEEL
saberio_rewind-1.0.3.post3.dist-info/entry_points.txt
saberio_rewind-1.0.3.post3.dist-info/top_level.txt
saberio_rewind-1.0.3.post3.dist-info/RECORD
