Metadata-Version: 2.1
Name: saberio-rewind
Version: 1.0.3.post3
Summary: Python script to download custom song from BSaber and add bookmark to it. 
Author-email: Moris Doratiotto <moris.doratiotto@gmail.com>, Felicia Wen <i@feli.cf>
Project-URL: Homepage, https://github.com/wmyfelix/PySaber
Project-URL: Bug Tracker, https://github.com/wmyfelix/PySaber/issues
Keywords: beat saber,bsaber,beat saver,spotify
Classifier: Programming Language :: Python :: 3
Classifier: License :: OSI Approved :: MIT License
Classifier: Operating System :: OS Independent
Classifier: Development Status :: 3 - Alpha
Classifier: Intended Audience :: Developers
Requires-Python: >=3.9
License-File: LICENSE
Requires-Dist: beautifulsoup4 (==4.11.1)
Requires-Dist: colorifix (==2.0.4)
Requires-Dist: pymortafix (==0.2.2)
Requires-Dist: halo (==0.0.31)
Requires-Dist: tabulate (==0.8.10)
Requires-Dist: wcwidth (==0.2.6)
Requires-Dist: spotipy (==2.22.1)
